ug100/__init__.py
ug100/dataset.py
ug100-1.0.0.dist-info/METADATA
ug100-1.0.0.dist-info/WHEEL
ug100-1.0.0.dist-info/licenses/LICENSE
ug100-1.0.0.dist-info/RECORD
