Metadata-Version: 2.1
Name: ug100
Version: 1.0.0
Summary: Dataset containing adversarial results for seven approximate attacks (+ MIP) on MNIST and CIFAR10.
Project-URL: Homepage, https://github.com/samuelemarro/ug100
Project-URL: Bug Tracker, https://github.com/samuelemarro/ug100
Author-email: Samuele Marro <marrosamuele@gmail.com>
License: MIT License
Keywords: adversarial,attack,cifar10,dataset,mip,mixed-integer programming,mnist
Classifier: License :: OSI Approved :: MIT License
Classifier: Operating System :: OS Independent
Classifier: Programming Language :: Python :: 3
Requires-Python: >=3.7
Requires-Dist: torch>=1.7.1
Requires-Dist: tqdm>=4.64.0
